README
setup.py
octopasty/__init__.py
octopasty/ami.py
octopasty/asterisk.py
octopasty/bubble.py
octopasty/configure.py
octopasty/docopt.py
octopasty/graph.py
octopasty/internal.py
octopasty/opasty.py
octopasty/pasty.py
octopasty.egg-info/PKG-INFO
octopasty.egg-info/SOURCES.txt
octopasty.egg-info/dependency_links.txt
octopasty.egg-info/entry_points.txt
octopasty.egg-info/requires.txt
octopasty.egg-info/top_level.txt
octopasty/../docs/diagram.odg
octopasty/../docs/diagram.png
octopasty/../docs/doc-example.py
octopasty/../docs/doc-log.py
octopasty/../docs/octopasty.org