Metadata-Version: 1.0
Name: octopasty
Version: 0.2
Summary: Octopasty Asterisk AMI proxy
Home-page: http://ubity.com
Author: Jean Schurger
Author-email: jean@schurger.org
License: GPLv3
Platform: UNKNOWN
